[
    {
        "username": "Ahmed",
        "type": "Rent",
        "days": "8",
        "id": 1,
        "title": "the begest",
        "description": " lorem ipsum dolor sit amet con et connexion dolore magna",
        "category": "action",
        "price": 19.99,
        "auther": "ahmed magdy",
        "publisher": "elshrouk"
    },
    {
        "username": "Mohaemd",
        "type": "Rent",
        "days": "8",
        "id": 2,
        "title": "the row",
        "description": "lorem ipsum dolor sit amet con et connexion dolore magna",
        "category": "gena",
        "price": 22.99,
        "auther": "gamal sabry",
        "publisher": "elshrouk"
    },
    {
        "username": "Yosseff",
        "type": "Rent",
        "days": "8",
        "id": 3,
        "title": "mind 5 minuts",
        "description": "fagfd ga dgga g",
        "price": 44.0,
        "auther": "hakem",
        "publisher": "koko and s",
        "category": "gg"
    },
    {
        "username": "hagar",
        "type": "Rent",
        "days": "8",
        "id": 1,
        "title": "the begest",
        "description": " lorem ipsum dolor sit amet con et connexion dolore magna",
        "price": 19.99,
        "auther": "ahmed magdy",
        "publisher": "elshrouk",
        "category": "action"
    },
    {
        "username": "madgy",
        "type": "Rent",
        "days": "5",
        "id": 2,
        "title": "the row",
        "description": "lorem ipsum dolor sit amet con et connexion dolore magna",
        "price": "22.99",
        "auther": "gamal sabry",
        "publisher": "elshrouk",
        "category": "gena"
    },
    {
        "username": "marwan fady",
        "type": "Rent",
        "days": "9",
        "id": 4,
        "title": "good days",
        "description": " lorem ipsum dolor sit amet con et connexion dolore magna",
        "price": "44.0",
        "auther": "hakem",
        "publisher": "koko and s",
        "category": "gg"
    },
    {
        "username": "mohameed",
        "type": "Rent",
        "days": "10",
        "id": 3,
        "title": "mind 5 minuts",
        "description": "fagfd ga dgga g",
        "price": "44.0",
        "auther": "hakem",
        "publisher": "koko and s",
        "category": "gg"
    },
    {
        "username": "jiji man",
        "type": "Rent",
        "days": "6",
        "id": 4,
        "title": "good days",
        "description": " lorem ipsum dolor sit amet con et connexion dolore magna",
        "price": "44.0",
        "auther": "hakem",
        "publisher": "koko and s",
        "category": "gg"
    }
]